README.txt
setup.py
Mip_Family_Analysis/__init__.py
Mip_Family_Analysis/Models/__init__.py
Mip_Family_Analysis/Models/genetic_models.py
Mip_Family_Analysis/Models/score_variants.py
Mip_Family_Analysis/Utils/__init__.py
Mip_Family_Analysis/Utils/annotation_parser.py
Mip_Family_Analysis/Utils/header_parser.py
Mip_Family_Analysis/Utils/is_number.py
Mip_Family_Analysis/Utils/pair_generator.py
Mip_Family_Analysis/Utils/variant_consumer.py
Mip_Family_Analysis/Utils/variant_printer.py
Mip_Family_Analysis/Utils/variant_sorter.py
Mip_Family_Analysis/Variants/__init__.py
Mip_Family_Analysis/Variants/genotype.py
Mip_Family_Analysis/Variants/variant_parser.py
mip_family_analysis.egg-info/PKG-INFO
mip_family_analysis.egg-info/SOURCES.txt
mip_family_analysis.egg-info/dependency_links.txt
mip_family_analysis.egg-info/requires.txt
mip_family_analysis.egg-info/top_level.txt
scripts/run_mip_family_analysis.py