Metadata-Version: 1.0
Name: mip-family-analysis
Version: 0.9.2
Summary: A new tool for doing inheritance analysis and scoring in the mip pipeline.
Home-page: https://github.com/moonso/Mip_Family_Analysis
Author: Mans Magnusson
Author-email: mans.magnusson@scilifelab.se
License: UNKNOWN
Platform: UNKNOWN
